{
  "lastUpdate": "2026-06-18T18:37:49+02:00",
  "source": "https://www.stadtradeln.de/rhein-neckar-kreis",
  "municipalities": [
    {
      "rank": 1,
      "name": "Weinheim im Rhein-Neckar-Kreis",
      "km": 39241,
      "kmFormatted": "39.241 km",
      "trips": 4328,
      "kmPerInhabitant": 0.12,
      "population": 45852,
      "url": "https://www.stadtradeln.de/weinheim"
    },
    {
      "rank": 2,
      "name": "Hockenheim im Rhein-Neckar-Kreis",
      "km": 28315,
      "kmFormatted": "28.315 km",
      "trips": 3572,
      "kmPerInhabitant": 0.0,
      "population": 21631,
      "url": "https://www.stadtradeln.de/hockenheim"
    },
    {
      "rank": 3,
      "name": "Wiesloch im Rhein-Neckar-Kreis",
      "km": 27407,
      "kmFormatted": "27.407 km",
      "trips": 1872,
      "kmPerInhabitant": 1.58,
      "population": 27665,
      "url": "https://www.stadtradeln.de/wiesloch"
    },
    {
      "rank": 4,
      "name": "Sinsheim im Rhein-Neckar-Kreis",
      "km": 23562,
      "kmFormatted": "23.562 km",
      "trips": 1699,
      "kmPerInhabitant": 1.75,
      "population": 37000,
      "url": "https://www.stadtradeln.de/sinsheim"
    },
    {
      "rank": 5,
      "name": "Ladenburg im Rhein-Neckar-Kreis",
      "km": 22300,
      "kmFormatted": "22.300 km",
      "trips": 1993,
      "kmPerInhabitant": 0.0,
      "population": 12500,
      "url": "https://www.stadtradeln.de/ladenburg"
    },
    {
      "rank": 6,
      "name": "Walldorf im Rhein-Neckar-Kreis",
      "km": 21477,
      "kmFormatted": "21.477 km",
      "trips": 2378,
      "kmPerInhabitant": 3.32,
      "population": 16220,
      "url": "https://www.stadtradeln.de/walldorf"
    },
    {
      "rank": 7,
      "name": "Schwetzingen im Rhein-Neckar-Kreis",
      "km": 20265,
      "kmFormatted": "20.265 km",
      "trips": 1951,
      "kmPerInhabitant": 1.02,
      "population": 21767,
      "url": "https://www.stadtradeln.de/schwetzingen"
    },
    {
      "rank": 8,
      "name": "Eschelbronn im Rhein-Neckar-Kreis",
      "km": 20105,
      "kmFormatted": "20.105 km",
      "trips": 856,
      "kmPerInhabitant": 45.53,
      "population": 2781,
      "url": "https://www.stadtradeln.de/eschelbronn"
    },
    {
      "rank": 9,
      "name": "Eberbach im Rhein-Neckar-Kreis",
      "km": 17148,
      "kmFormatted": "17.148 km",
      "trips": 1345,
      "kmPerInhabitant": 1.34,
      "population": 14760,
      "url": "https://www.stadtradeln.de/eberbach"
    },
    {
      "rank": 10,
      "name": "Eppelheim im Rhein-Neckar-Kreis",
      "km": 16780,
      "kmFormatted": "16.780 km",
      "trips": 2020,
      "kmPerInhabitant": 14.13,
      "population": 16046,
      "url": "https://www.stadtradeln.de/eppelheim"
    },
    {
      "rank": 11,
      "name": "Neckargemünd im Rhein-Neckar-Kreis",
      "km": 16752,
      "kmFormatted": "16.752 km",
      "trips": 1300,
      "kmPerInhabitant": 0.11,
      "population": 13595,
      "url": "https://www.stadtradeln.de/neckargemuend"
    },
    {
      "rank": 12,
      "name": "Hirschberg im Rhein-Neckar-Kreis",
      "km": 14934,
      "kmFormatted": "14.934 km",
      "trips": 1175,
      "kmPerInhabitant": 0.0,
      "population": 9550,
      "url": "https://www.stadtradeln.de/hirschberg"
    },
    {
      "rank": 13,
      "name": "Brühl/Baden im Rhein-Neckar-Kreis",
      "km": 14825,
      "kmFormatted": "14.825 km",
      "trips": 1111,
      "kmPerInhabitant": 0.46,
      "population": 14624,
      "url": "https://www.stadtradeln.de/bruehl-baden"
    },
    {
      "rank": 14,
      "name": "Ketsch im Rhein-Neckar-Kreis",
      "km": 14408,
      "kmFormatted": "14.408 km",
      "trips": 1043,
      "kmPerInhabitant": 0.0,
      "population": 13007,
      "url": "https://www.stadtradeln.de/ketsch"
    },
    {
      "rank": 15,
      "name": "Heddesheim im Rhein-Neckar-Kreis",
      "km": 11978,
      "kmFormatted": "11.978 km",
      "trips": 785,
      "kmPerInhabitant": 0.98,
      "population": 12343,
      "url": "https://www.stadtradeln.de/heddesheim"
    },
    {
      "rank": 16,
      "name": "Schriesheim im Rhein-Neckar-Kreis",
      "km": 11030,
      "kmFormatted": "11.030 km",
      "trips": 1206,
      "kmPerInhabitant": 0.1,
      "population": 15331,
      "url": "https://www.stadtradeln.de/schriesheim"
    },
    {
      "rank": 17,
      "name": "Sandhausen im Rhein-Neckar-Kreis",
      "km": 10489,
      "kmFormatted": "10.489 km",
      "trips": 1132,
      "kmPerInhabitant": 0.29,
      "population": 15500,
      "url": "https://www.stadtradeln.de/sandhausen"
    },
    {
      "rank": 18,
      "name": "St. Leon-Rot im Rhein-Neckar-Kreis",
      "km": 10262,
      "kmFormatted": "10.262 km",
      "trips": 729,
      "kmPerInhabitant": 0.0,
      "population": 14036,
      "url": "https://www.stadtradeln.de/st-leon-rot"
    },
    {
      "rank": 19,
      "name": "Dossenheim im Rhein-Neckar-Kreis",
      "km": 9811,
      "kmFormatted": "9.811 km",
      "trips": 1217,
      "kmPerInhabitant": 3.23,
      "population": 12543,
      "url": "https://www.stadtradeln.de/dossenheim"
    },
    {
      "rank": 20,
      "name": "Edingen-Neckarhausen im Rhein-Neckar-Kreis",
      "km": 9028,
      "kmFormatted": "9.028 km",
      "trips": 1053,
      "kmPerInhabitant": 0.0,
      "population": 14612,
      "url": "https://www.stadtradeln.de/edingen-neckarhausen"
    },
    {
      "rank": 21,
      "name": "Neulußheim im Rhein-Neckar-Kreis",
      "km": 8904,
      "kmFormatted": "8.904 km",
      "trips": 628,
      "kmPerInhabitant": 0.06,
      "population": 7300,
      "url": "https://www.stadtradeln.de/neulussheim"
    },
    {
      "rank": 22,
      "name": "Helmstadt-Bargen im Rhein-Neckar-Kreis",
      "km": 8811,
      "kmFormatted": "8.811 km",
      "trips": 614,
      "kmPerInhabitant": 0.4,
      "population": 3923,
      "url": "https://www.stadtradeln.de/helmstadt-bargen"
    },
    {
      "rank": 23,
      "name": "Laudenbach im Rhein-Neckar-Kreis",
      "km": 8383,
      "kmFormatted": "8.383 km",
      "trips": 673,
      "kmPerInhabitant": 0.0,
      "population": 6556,
      "url": "https://www.stadtradeln.de/laudenbach"
    },
    {
      "rank": 24,
      "name": "Meckesheim im Rhein-Neckar-Kreis",
      "km": 6517,
      "kmFormatted": "6.517 km",
      "trips": 434,
      "kmPerInhabitant": 0.34,
      "population": 5400,
      "url": "https://www.stadtradeln.de/meckesheim"
    },
    {
      "rank": 25,
      "name": "Rauenberg im Rhein-Neckar-Kreis",
      "km": 5714,
      "kmFormatted": "5.714 km",
      "trips": 433,
      "kmPerInhabitant": 0.51,
      "population": 8728,
      "url": "https://www.stadtradeln.de/rauenberg"
    },
    {
      "rank": 26,
      "name": "Schönau im Rhein-Neckar-Kreis",
      "km": 5523,
      "kmFormatted": "5.523 km",
      "trips": 358,
      "kmPerInhabitant": 0.0,
      "population": 4330,
      "url": "https://www.stadtradeln.de/schoenau"
    },
    {
      "rank": 27,
      "name": "Plankstadt im Rhein-Neckar-Kreis",
      "km": 5424,
      "kmFormatted": "5.424 km",
      "trips": 622,
      "kmPerInhabitant": 0.95,
      "population": 10720,
      "url": "https://www.stadtradeln.de/plankstadt"
    },
    {
      "rank": 28,
      "name": "Oftersheim im Rhein-Neckar-Kreis",
      "km": 5414,
      "kmFormatted": "5.414 km",
      "trips": 478,
      "kmPerInhabitant": 0.05,
      "population": 12272,
      "url": "https://www.stadtradeln.de/oftersheim"
    },
    {
      "rank": 29,
      "name": "Leimen im Rhein-Neckar-Kreis",
      "km": 5182,
      "kmFormatted": "5.182 km",
      "trips": 555,
      "kmPerInhabitant": 0.0,
      "population": 26873,
      "url": "https://www.stadtradeln.de/leimen"
    },
    {
      "rank": 30,
      "name": "Neidenstein im Rhein-Neckar-Kreis",
      "km": 4779,
      "kmFormatted": "4.779 km",
      "trips": 219,
      "kmPerInhabitant": 4.4,
      "population": 1750,
      "url": "https://www.stadtradeln.de/neidenstein"
    },
    {
      "rank": 31,
      "name": "Dielheim im Rhein-Neckar-Kreis",
      "km": 4341,
      "kmFormatted": "4.341 km",
      "trips": 294,
      "kmPerInhabitant": 0.0,
      "population": 910,
      "url": "https://www.stadtradeln.de/dielheim"
    },
    {
      "rank": 32,
      "name": "Ilvesheim im Rhein-Neckar-Kreis",
      "km": 4317,
      "kmFormatted": "4.317 km",
      "trips": 452,
      "kmPerInhabitant": 0.0,
      "population": 9254,
      "url": "https://www.stadtradeln.de/ilvesheim"
    },
    {
      "rank": 33,
      "name": "Mauer im Rhein-Neckar-Kreis",
      "km": 3978,
      "kmFormatted": "3.978 km",
      "trips": 244,
      "kmPerInhabitant": 9.53,
      "population": 4075,
      "url": "https://www.stadtradeln.de/mauer"
    },
    {
      "rank": 34,
      "name": "Waibstadt im Rhein-Neckar-Kreis",
      "km": 3938,
      "kmFormatted": "3.938 km",
      "trips": 250,
      "kmPerInhabitant": 1.16,
      "population": 5803,
      "url": "https://www.stadtradeln.de/waibstadt"
    },
    {
      "rank": 35,
      "name": "Nußloch im Rhein-Neckar-Kreis",
      "km": 3818,
      "kmFormatted": "3.818 km",
      "trips": 309,
      "kmPerInhabitant": 0.5,
      "population": 11397,
      "url": "https://www.stadtradeln.de/nussloch"
    },
    {
      "rank": 36,
      "name": "Neckarbischofsheim im Rhein-Neckar-Kreis",
      "km": 3810,
      "kmFormatted": "3.810 km",
      "trips": 356,
      "kmPerInhabitant": 0.0,
      "population": 4195,
      "url": "https://www.stadtradeln.de/neckarbischofsheim"
    },
    {
      "rank": 37,
      "name": "Schönbrunn im Rhein-Neckar-Kreis",
      "km": 3798,
      "kmFormatted": "3.798 km",
      "trips": 173,
      "kmPerInhabitant": 0.0,
      "population": 2963,
      "url": "https://www.stadtradeln.de/schoenbrunn"
    },
    {
      "rank": 38,
      "name": "Mühlhausen im Rhein-Neckar-Kreis",
      "km": 3462,
      "kmFormatted": "3.462 km",
      "trips": 207,
      "kmPerInhabitant": 0.0,
      "population": 8767,
      "url": "https://www.stadtradeln.de/muehlhausen"
    },
    {
      "rank": 39,
      "name": "Lobbach im Rhein-Neckar-Kreis",
      "km": 3086,
      "kmFormatted": "3.086 km",
      "trips": 146,
      "kmPerInhabitant": 0.0,
      "population": 232,
      "url": "https://www.stadtradeln.de/lobbach"
    },
    {
      "rank": 40,
      "name": "Malsch im Rhein-Neckar-Kreis",
      "km": 3081,
      "kmFormatted": "3.081 km",
      "trips": 257,
      "kmPerInhabitant": 0.65,
      "population": 3524,
      "url": "https://www.stadtradeln.de/malsch-weinort"
    },
    {
      "rank": 41,
      "name": "Altlußheim im Rhein-Neckar-Kreis",
      "km": 3068,
      "kmFormatted": "3.068 km",
      "trips": 280,
      "kmPerInhabitant": 1.58,
      "population": 6416,
      "url": "https://www.stadtradeln.de/altlussheim"
    },
    {
      "rank": 42,
      "name": "Angelbachtal im Rhein-Neckar-Kreis",
      "km": 2918,
      "kmFormatted": "2.918 km",
      "trips": 221,
      "kmPerInhabitant": 0.0,
      "population": 5200,
      "url": "https://www.stadtradeln.de/angelbachtal"
    },
    {
      "rank": 43,
      "name": "Reilingen im Rhein-Neckar-Kreis",
      "km": 2808,
      "kmFormatted": "2.808 km",
      "trips": 389,
      "kmPerInhabitant": 0.0,
      "population": 8244,
      "url": "https://www.stadtradeln.de/reilingen"
    },
    {
      "rank": 44,
      "name": "Epfenbach im Rhein-Neckar-Kreis",
      "km": 2553,
      "kmFormatted": "2.553 km",
      "trips": 115,
      "kmPerInhabitant": 0.0,
      "population": 2430,
      "url": "https://www.stadtradeln.de/epfenbach"
    },
    {
      "rank": 45,
      "name": "Hemsbach im Rhein-Neckar-Kreis",
      "km": 2488,
      "kmFormatted": "2.488 km",
      "trips": 254,
      "kmPerInhabitant": 0.12,
      "population": 11987,
      "url": "https://www.stadtradeln.de/hemsbach"
    },
    {
      "rank": 46,
      "name": "Gaiberg im Rhein-Neckar-Kreis",
      "km": 1251,
      "kmFormatted": "1.251 km",
      "trips": 34,
      "kmPerInhabitant": 0.0,
      "population": 2499,
      "url": "https://www.stadtradeln.de/gaiberg"
    },
    {
      "rank": 47,
      "name": "Wiesenbach im Rhein-Neckar-Kreis",
      "km": 1220,
      "kmFormatted": "1.220 km",
      "trips": 120,
      "kmPerInhabitant": 0.0,
      "population": 3169,
      "url": "https://www.stadtradeln.de/wiesenbach"
    },
    {
      "rank": 48,
      "name": "Wilhelmsfeld im Rhein-Neckar-Kreis",
      "km": 894,
      "kmFormatted": "894 km",
      "trips": 79,
      "kmPerInhabitant": 0.0,
      "population": 3377,
      "url": "https://www.stadtradeln.de/wilhelmsfeld"
    },
    {
      "rank": 49,
      "name": "Spechbach im Rhein-Neckar-Kreis",
      "km": 817,
      "kmFormatted": "817 km",
      "trips": 38,
      "kmPerInhabitant": 0.0,
      "population": 1757,
      "url": "https://www.stadtradeln.de/spechbach"
    },
    {
      "rank": 50,
      "name": "Zuzenhausen im Rhein-Neckar-Kreis",
      "km": 791,
      "kmFormatted": "791 km",
      "trips": 33,
      "kmPerInhabitant": 0.0,
      "population": 2416,
      "url": "https://www.stadtradeln.de/zuzenhausen"
    },
    {
      "rank": 51,
      "name": "Heiligkreuzsteinach im Rhein-Neckar-Kreis",
      "km": 338,
      "kmFormatted": "338 km",
      "trips": 10,
      "kmPerInhabitant": 0.0,
      "population": 2601,
      "url": "https://www.stadtradeln.de/heiligkreuzsteinach"
    },
    {
      "rank": 52,
      "name": "Bammental im Rhein-Neckar-Kreis",
      "km": 186,
      "kmFormatted": "186 km",
      "trips": 7,
      "kmPerInhabitant": 0.0,
      "population": 6282,
      "url": "https://www.stadtradeln.de/bammental"
    },
    {
      "rank": 53,
      "name": "Heddesbach im Rhein-Neckar-Kreis",
      "km": 0,
      "kmFormatted": "0 km",
      "trips": 0,
      "kmPerInhabitant": 0.0,
      "population": 489,
      "url": "https://www.stadtradeln.de/heddesbach"
    }
  ]
}