{
  "lastUpdate": "2026-07-03T12:08:18+02:00",
  "source": "https://www.stadtradeln.de/rhein-neckar-kreis",
  "municipalities": [
    {
      "rank": 1,
      "name": "Weinheim im Rhein-Neckar-Kreis",
      "km": 160782,
      "kmFormatted": "160.782 km",
      "trips": 18983,
      "kmPerInhabitant": 0.71,
      "population": 45852,
      "url": "https://www.stadtradeln.de/weinheim"
    },
    {
      "rank": 2,
      "name": "Hockenheim im Rhein-Neckar-Kreis",
      "km": 115813,
      "kmFormatted": "115.813 km",
      "trips": 13876,
      "kmPerInhabitant": 0.0,
      "population": 21631,
      "url": "https://www.stadtradeln.de/hockenheim"
    },
    {
      "rank": 3,
      "name": "Ladenburg im Rhein-Neckar-Kreis",
      "km": 114983,
      "kmFormatted": "114.983 km",
      "trips": 9646,
      "kmPerInhabitant": 0.0,
      "population": 12500,
      "url": "https://www.stadtradeln.de/ladenburg"
    },
    {
      "rank": 4,
      "name": "Wiesloch im Rhein-Neckar-Kreis",
      "km": 106563,
      "kmFormatted": "106.563 km",
      "trips": 7750,
      "kmPerInhabitant": 7.48,
      "population": 27665,
      "url": "https://www.stadtradeln.de/wiesloch"
    },
    {
      "rank": 5,
      "name": "Walldorf im Rhein-Neckar-Kreis",
      "km": 97608,
      "kmFormatted": "97.608 km",
      "trips": 11074,
      "kmPerInhabitant": 13.78,
      "population": 16220,
      "url": "https://www.stadtradeln.de/walldorf"
    },
    {
      "rank": 6,
      "name": "Sinsheim im Rhein-Neckar-Kreis",
      "km": 95907,
      "kmFormatted": "95.907 km",
      "trips": 6558,
      "kmPerInhabitant": 12.78,
      "population": 37000,
      "url": "https://www.stadtradeln.de/sinsheim"
    },
    {
      "rank": 7,
      "name": "Schwetzingen im Rhein-Neckar-Kreis",
      "km": 78528,
      "kmFormatted": "78.528 km",
      "trips": 7942,
      "kmPerInhabitant": 3.86,
      "population": 21767,
      "url": "https://www.stadtradeln.de/schwetzingen"
    },
    {
      "rank": 8,
      "name": "Eberbach im Rhein-Neckar-Kreis",
      "km": 68578,
      "kmFormatted": "68.578 km",
      "trips": 4860,
      "kmPerInhabitant": 4.65,
      "population": 14760,
      "url": "https://www.stadtradeln.de/eberbach"
    },
    {
      "rank": 9,
      "name": "Eschelbronn im Rhein-Neckar-Kreis",
      "km": 68464,
      "kmFormatted": "68.464 km",
      "trips": 3060,
      "kmPerInhabitant": 323.8,
      "population": 2781,
      "url": "https://www.stadtradeln.de/eschelbronn"
    },
    {
      "rank": 10,
      "name": "Neckargemünd im Rhein-Neckar-Kreis",
      "km": 67905,
      "kmFormatted": "67.905 km",
      "trips": 5339,
      "kmPerInhabitant": 0.19,
      "population": 13595,
      "url": "https://www.stadtradeln.de/neckargemuend"
    },
    {
      "rank": 11,
      "name": "Eppelheim im Rhein-Neckar-Kreis",
      "km": 67743,
      "kmFormatted": "67.743 km",
      "trips": 8029,
      "kmPerInhabitant": 46.7,
      "population": 16046,
      "url": "https://www.stadtradeln.de/eppelheim"
    },
    {
      "rank": 12,
      "name": "Brühl/Baden im Rhein-Neckar-Kreis",
      "km": 59790,
      "kmFormatted": "59.790 km",
      "trips": 5193,
      "kmPerInhabitant": 2.25,
      "population": 14624,
      "url": "https://www.stadtradeln.de/bruehl-baden"
    },
    {
      "rank": 13,
      "name": "Hirschberg im Rhein-Neckar-Kreis",
      "km": 56069,
      "kmFormatted": "56.069 km",
      "trips": 4678,
      "kmPerInhabitant": 0.0,
      "population": 9550,
      "url": "https://www.stadtradeln.de/hirschberg"
    },
    {
      "rank": 14,
      "name": "Ketsch im Rhein-Neckar-Kreis",
      "km": 55215,
      "kmFormatted": "55.215 km",
      "trips": 4457,
      "kmPerInhabitant": 0.0,
      "population": 13007,
      "url": "https://www.stadtradeln.de/ketsch"
    },
    {
      "rank": 15,
      "name": "Schriesheim im Rhein-Neckar-Kreis",
      "km": 49077,
      "kmFormatted": "49.077 km",
      "trips": 5084,
      "kmPerInhabitant": 15.61,
      "population": 15331,
      "url": "https://www.stadtradeln.de/schriesheim"
    },
    {
      "rank": 16,
      "name": "Heddesheim im Rhein-Neckar-Kreis",
      "km": 48625,
      "kmFormatted": "48.625 km",
      "trips": 3120,
      "kmPerInhabitant": 1.81,
      "population": 12343,
      "url": "https://www.stadtradeln.de/heddesheim"
    },
    {
      "rank": 17,
      "name": "Sandhausen im Rhein-Neckar-Kreis",
      "km": 44495,
      "kmFormatted": "44.495 km",
      "trips": 4834,
      "kmPerInhabitant": 1.34,
      "population": 15500,
      "url": "https://www.stadtradeln.de/sandhausen"
    },
    {
      "rank": 18,
      "name": "Edingen-Neckarhausen im Rhein-Neckar-Kreis",
      "km": 42337,
      "kmFormatted": "42.337 km",
      "trips": 4326,
      "kmPerInhabitant": 0.58,
      "population": 14612,
      "url": "https://www.stadtradeln.de/edingen-neckarhausen"
    },
    {
      "rank": 19,
      "name": "St. Leon-Rot im Rhein-Neckar-Kreis",
      "km": 41257,
      "kmFormatted": "41.257 km",
      "trips": 3197,
      "kmPerInhabitant": 0.19,
      "population": 14036,
      "url": "https://www.stadtradeln.de/st-leon-rot"
    },
    {
      "rank": 20,
      "name": "Dossenheim im Rhein-Neckar-Kreis",
      "km": 39778,
      "kmFormatted": "39.778 km",
      "trips": 4988,
      "kmPerInhabitant": 29.13,
      "population": 12543,
      "url": "https://www.stadtradeln.de/dossenheim"
    },
    {
      "rank": 21,
      "name": "Neulußheim im Rhein-Neckar-Kreis",
      "km": 38108,
      "kmFormatted": "38.108 km",
      "trips": 2574,
      "kmPerInhabitant": 2.13,
      "population": 7300,
      "url": "https://www.stadtradeln.de/neulussheim"
    },
    {
      "rank": 22,
      "name": "Helmstadt-Bargen im Rhein-Neckar-Kreis",
      "km": 36113,
      "kmFormatted": "36.113 km",
      "trips": 2201,
      "kmPerInhabitant": 1.62,
      "population": 3923,
      "url": "https://www.stadtradeln.de/helmstadt-bargen"
    },
    {
      "rank": 23,
      "name": "Laudenbach im Rhein-Neckar-Kreis",
      "km": 29843,
      "kmFormatted": "29.843 km",
      "trips": 2562,
      "kmPerInhabitant": 0.0,
      "population": 6556,
      "url": "https://www.stadtradeln.de/laudenbach"
    },
    {
      "rank": 24,
      "name": "Meckesheim im Rhein-Neckar-Kreis",
      "km": 26467,
      "kmFormatted": "26.467 km",
      "trips": 1687,
      "kmPerInhabitant": 1.02,
      "population": 5400,
      "url": "https://www.stadtradeln.de/meckesheim"
    },
    {
      "rank": 25,
      "name": "Leimen im Rhein-Neckar-Kreis",
      "km": 24729,
      "kmFormatted": "24.729 km",
      "trips": 2628,
      "kmPerInhabitant": 0.0,
      "population": 26873,
      "url": "https://www.stadtradeln.de/leimen"
    },
    {
      "rank": 26,
      "name": "Neidenstein im Rhein-Neckar-Kreis",
      "km": 21549,
      "kmFormatted": "21.549 km",
      "trips": 869,
      "kmPerInhabitant": 26.22,
      "population": 1750,
      "url": "https://www.stadtradeln.de/neidenstein"
    },
    {
      "rank": 27,
      "name": "Plankstadt im Rhein-Neckar-Kreis",
      "km": 21204,
      "kmFormatted": "21.204 km",
      "trips": 2405,
      "kmPerInhabitant": 5.7,
      "population": 10720,
      "url": "https://www.stadtradeln.de/plankstadt"
    },
    {
      "rank": 28,
      "name": "Rauenberg im Rhein-Neckar-Kreis",
      "km": 19798,
      "kmFormatted": "19.798 km",
      "trips": 1543,
      "kmPerInhabitant": 0.95,
      "population": 8728,
      "url": "https://www.stadtradeln.de/rauenberg"
    },
    {
      "rank": 29,
      "name": "Oftersheim im Rhein-Neckar-Kreis",
      "km": 19079,
      "kmFormatted": "19.079 km",
      "trips": 1765,
      "kmPerInhabitant": 0.22,
      "population": 12272,
      "url": "https://www.stadtradeln.de/oftersheim"
    },
    {
      "rank": 30,
      "name": "Nußloch im Rhein-Neckar-Kreis",
      "km": 18152,
      "kmFormatted": "18.152 km",
      "trips": 1413,
      "kmPerInhabitant": 1.79,
      "population": 11397,
      "url": "https://www.stadtradeln.de/nussloch"
    },
    {
      "rank": 31,
      "name": "Schönau im Rhein-Neckar-Kreis",
      "km": 17842,
      "kmFormatted": "17.842 km",
      "trips": 1018,
      "kmPerInhabitant": 0.0,
      "population": 4330,
      "url": "https://www.stadtradeln.de/schoenau"
    },
    {
      "rank": 32,
      "name": "Dielheim im Rhein-Neckar-Kreis",
      "km": 16366,
      "kmFormatted": "16.366 km",
      "trips": 1099,
      "kmPerInhabitant": 0.0,
      "population": 910,
      "url": "https://www.stadtradeln.de/dielheim"
    },
    {
      "rank": 33,
      "name": "Ilvesheim im Rhein-Neckar-Kreis",
      "km": 15871,
      "kmFormatted": "15.871 km",
      "trips": 1605,
      "kmPerInhabitant": 0.0,
      "population": 9254,
      "url": "https://www.stadtradeln.de/ilvesheim"
    },
    {
      "rank": 34,
      "name": "Schönbrunn im Rhein-Neckar-Kreis",
      "km": 15805,
      "kmFormatted": "15.805 km",
      "trips": 595,
      "kmPerInhabitant": 0.0,
      "population": 2963,
      "url": "https://www.stadtradeln.de/schoenbrunn"
    },
    {
      "rank": 35,
      "name": "Waibstadt im Rhein-Neckar-Kreis",
      "km": 14448,
      "kmFormatted": "14.448 km",
      "trips": 876,
      "kmPerInhabitant": 5.37,
      "population": 5803,
      "url": "https://www.stadtradeln.de/waibstadt"
    },
    {
      "rank": 36,
      "name": "Mühlhausen im Rhein-Neckar-Kreis",
      "km": 12865,
      "kmFormatted": "12.865 km",
      "trips": 790,
      "kmPerInhabitant": 0.0,
      "population": 8767,
      "url": "https://www.stadtradeln.de/muehlhausen"
    },
    {
      "rank": 37,
      "name": "Mauer im Rhein-Neckar-Kreis",
      "km": 12672,
      "kmFormatted": "12.672 km",
      "trips": 756,
      "kmPerInhabitant": 21.33,
      "population": 4075,
      "url": "https://www.stadtradeln.de/mauer"
    },
    {
      "rank": 38,
      "name": "Reilingen im Rhein-Neckar-Kreis",
      "km": 12601,
      "kmFormatted": "12.601 km",
      "trips": 1752,
      "kmPerInhabitant": 0.0,
      "population": 8244,
      "url": "https://www.stadtradeln.de/reilingen"
    },
    {
      "rank": 39,
      "name": "Neckarbischofsheim im Rhein-Neckar-Kreis",
      "km": 12056,
      "kmFormatted": "12.056 km",
      "trips": 1060,
      "kmPerInhabitant": 0.0,
      "population": 4195,
      "url": "https://www.stadtradeln.de/neckarbischofsheim"
    },
    {
      "rank": 40,
      "name": "Malsch im Rhein-Neckar-Kreis",
      "km": 11654,
      "kmFormatted": "11.654 km",
      "trips": 997,
      "kmPerInhabitant": 3.9,
      "population": 3524,
      "url": "https://www.stadtradeln.de/malsch-weinort"
    },
    {
      "rank": 41,
      "name": "Altlußheim im Rhein-Neckar-Kreis",
      "km": 10252,
      "kmFormatted": "10.252 km",
      "trips": 925,
      "kmPerInhabitant": 3.18,
      "population": 6416,
      "url": "https://www.stadtradeln.de/altlussheim"
    },
    {
      "rank": 42,
      "name": "Hemsbach im Rhein-Neckar-Kreis",
      "km": 10140,
      "kmFormatted": "10.140 km",
      "trips": 1280,
      "kmPerInhabitant": 0.36,
      "population": 11987,
      "url": "https://www.stadtradeln.de/hemsbach"
    },
    {
      "rank": 43,
      "name": "Angelbachtal im Rhein-Neckar-Kreis",
      "km": 9538,
      "kmFormatted": "9.538 km",
      "trips": 1002,
      "kmPerInhabitant": 0.0,
      "population": 5200,
      "url": "https://www.stadtradeln.de/angelbachtal"
    },
    {
      "rank": 44,
      "name": "Lobbach im Rhein-Neckar-Kreis",
      "km": 9500,
      "kmFormatted": "9.500 km",
      "trips": 472,
      "kmPerInhabitant": 0.0,
      "population": 232,
      "url": "https://www.stadtradeln.de/lobbach"
    },
    {
      "rank": 45,
      "name": "Epfenbach im Rhein-Neckar-Kreis",
      "km": 9205,
      "kmFormatted": "9.205 km",
      "trips": 404,
      "kmPerInhabitant": 0.0,
      "population": 2430,
      "url": "https://www.stadtradeln.de/epfenbach"
    },
    {
      "rank": 46,
      "name": "Wiesenbach im Rhein-Neckar-Kreis",
      "km": 6478,
      "kmFormatted": "6.478 km",
      "trips": 557,
      "kmPerInhabitant": 0.0,
      "population": 3169,
      "url": "https://www.stadtradeln.de/wiesenbach"
    },
    {
      "rank": 47,
      "name": "Wilhelmsfeld im Rhein-Neckar-Kreis",
      "km": 4942,
      "kmFormatted": "4.942 km",
      "trips": 311,
      "kmPerInhabitant": 0.0,
      "population": 3377,
      "url": "https://www.stadtradeln.de/wilhelmsfeld"
    },
    {
      "rank": 48,
      "name": "Gaiberg im Rhein-Neckar-Kreis",
      "km": 4089,
      "kmFormatted": "4.089 km",
      "trips": 128,
      "kmPerInhabitant": 0.0,
      "population": 2499,
      "url": "https://www.stadtradeln.de/gaiberg"
    },
    {
      "rank": 49,
      "name": "Spechbach im Rhein-Neckar-Kreis",
      "km": 3799,
      "kmFormatted": "3.799 km",
      "trips": 184,
      "kmPerInhabitant": 0.0,
      "population": 1757,
      "url": "https://www.stadtradeln.de/spechbach"
    },
    {
      "rank": 50,
      "name": "Zuzenhausen im Rhein-Neckar-Kreis",
      "km": 3467,
      "kmFormatted": "3.467 km",
      "trips": 149,
      "kmPerInhabitant": 0.0,
      "population": 2416,
      "url": "https://www.stadtradeln.de/zuzenhausen"
    },
    {
      "rank": 51,
      "name": "Heiligkreuzsteinach im Rhein-Neckar-Kreis",
      "km": 1121,
      "kmFormatted": "1.121 km",
      "trips": 43,
      "kmPerInhabitant": 0.0,
      "population": 2601,
      "url": "https://www.stadtradeln.de/heiligkreuzsteinach"
    },
    {
      "rank": 52,
      "name": "Bammental im Rhein-Neckar-Kreis",
      "km": 332,
      "kmFormatted": "332 km",
      "trips": 20,
      "kmPerInhabitant": 0.0,
      "population": 6282,
      "url": "https://www.stadtradeln.de/bammental"
    },
    {
      "rank": 53,
      "name": "Heddesbach im Rhein-Neckar-Kreis",
      "km": 0,
      "kmFormatted": "0 km",
      "trips": 0,
      "kmPerInhabitant": 0.0,
      "population": 489,
      "url": "https://www.stadtradeln.de/heddesbach"
    }
  ]
}